datasette_cldf/__init__.py
datasette_cldf/commands/__init__.py
datasette_cldf/commands/serve.py
datasette_cldf/static/cldf.css
datasette_cldf/static/cldf.js
datasette_cldf/templates/row.html
datasette_cldf-0.3.0.dist-info/licenses/LICENSE
datasette_cldf-0.3.0.dist-info/METADATA
datasette_cldf-0.3.0.dist-info/WHEEL
datasette_cldf-0.3.0.dist-info/entry_points.txt
datasette_cldf-0.3.0.dist-info/top_level.txt
datasette_cldf-0.3.0.dist-info/RECORD
