Metadata-Version: 2.4
Name: datasette-cldf
Version: 0.3.0
Summary: datasette plugin to explore CLDF datasets
Home-page: https://github.com/cldf/datasette-cldf
Author: Robert Forkel
Author-email: robert_forkel@eva.mpg.de
License: Apache 2.0
Keywords: linguistics
Platform: any
Classifier: Development Status :: 5 - Production/Stable
Classifier: Intended Audience :: Developers
Classifier: Intended Audience :: Science/Research
Classifier: Natural Language :: English
Classifier: Operating System :: OS Independent
Classifier: Programming Language :: Python :: 3
Classifier: Programming Language :: Python :: 3.10
Classifier: Programming Language :: Python :: 3.11
Classifier: Programming Language :: Python :: 3.12
Classifier: Programming Language :: Python :: 3.13
Classifier: Programming Language :: Python :: Implementation :: CPython
Classifier: Programming Language :: Python :: Implementation :: PyPy
Classifier: License :: OSI Approved :: Apache Software License
Requires-Python: >=3.10
License-File: LICENSE
Requires-Dist: datasette
Requires-Dist: datasette-template-sql
Requires-Dist: datasette-cluster-map
Requires-Dist: pycldf>=1.12.1
Requires-Dist: cldfbench
Requires-Dist: clldutils
Requires-Dist: uritemplate
Requires-Dist: zenodoclient>=0.3
Provides-Extra: dev
Requires-Dist: flake8; extra == "dev"
Requires-Dist: wheel; extra == "dev"
Requires-Dist: twine; extra == "dev"
Requires-Dist: build; extra == "dev"
Provides-Extra: test
Requires-Dist: asgiref; extra == "test"
Requires-Dist: pytest; extra == "test"
Requires-Dist: pytest-mock; extra == "test"
Requires-Dist: pytest-cov; extra == "test"
Dynamic: license-file
